{
  "project_info": {
    "project_number": "73624092539",
    "project_id": "tarp-f8f94",
    "storage_bucket": "tarp-f8f94.appspot.com"
  },
  "client": [
    {
      "client_info": {
        "mobilesdk_app_id": "1:73624092539:android:a1eeef9ee758cce52007de",
        "android_client_info": {
          "package_name": "com.example.tarp_app"
        }
      },
      "oauth_client": [
        {
          "client_id": "73624092539-ktkss8gh7ifiird723u3q1fvdacgrjvr.apps.googleusercontent.com",
          "client_type": 3
        }
      ],
      "api_key": [
        {
          "current_key": "AIzaSyBqpLSiJmhER-xEQ0hBeASiTD6lOUL1f2E"
        }
      ],
      "services": {
        "appinvite_service": {
          "other_platform_oauth_client": [
            {
              "client_id": "73624092539-ktkss8gh7ifiird723u3q1fvdacgrjvr.apps.googleusercontent.com",
              "client_type": 3
            }
          ]
        }
      }
    }
  ],
  "configuration_version": "1"
}